flexarray/__init__.py
flexarray/array.py
flexarray/mathematics.py
flexarray/searching.py
flexarray/sorting.py
flexarray-0.1.1.dist-info/LICENSE
flexarray-0.1.1.dist-info/METADATA
flexarray-0.1.1.dist-info/WHEEL
flexarray-0.1.1.dist-info/top_level.txt
flexarray-0.1.1.dist-info/RECORD
