Metadata-Version: 2.1
Name: flexarray
Version: 0.1.1
Summary: A Python library for static arrays with dynamic memory allocation like malloc, realloc, and free, and various array operations like searching, sorting, and mathematics.
Home-page: https://github.com/shashankpandey04/flexarray
Author: Shashank Pandey
Author-email: jpshashank200@gmail.com
License: MIT
Classifier: Programming Language :: Python :: 3
Classifier: License :: OSI Approved :: MIT License
Classifier: Operating System :: OS Independent
Requires-Python: >=3.6
License-File: LICENSE
